Metadata-Version: 1.1
Name: datecalculator
Version: 0.0.1
Summary: calculate how many years,month and days between time you entered and now 
Home-page: UNKNOWN
Author: mohammed yasser
Author-email: muhammedyasser85@gmail.com
License: MIT
Keywords: date calculator
Platform: UNKNOWN
Classifier: Development Status :: 5 - Production/Stable
Classifier: Intended Audience :: Education
Classifier: Operating System :: Microsoft :: Windows :: Windows 10
Classifier: License :: OSI Approved :: MIT License
Classifier: Programming Language :: Python :: 3
